HyperUserAgent/__init__.py
HyperUserAgent/main.py
HyperUserAgent/config/__init__.py
HyperUserAgent/config/browsers.json
HyperUserAgent/config/os.json
HyperUserAgent/config/weights.yaml
HyperUserAgent/core/__init__.py
HyperUserAgent/core/canvas.py
HyperUserAgent/core/fingerprint.py
HyperUserAgent/core/http2.py
HyperUserAgent/core/tls.py
HyperUserAgent/core/ua.py
HyperUserAgent/core/webgl.py
HyperUserAgent/network/__init__.py
HyperUserAgent/network/proxy.py
HyperUserAgent/network/session.py
HyperUserAgent/util/__init__.py
HyperUserAgent/util/loader.py
hyperuseragent-1.1.1.dist-info/licenses/LICENSE
hyperuseragent-1.1.1.dist-info/METADATA
hyperuseragent-1.1.1.dist-info/WHEEL
hyperuseragent-1.1.1.dist-info/top_level.txt
hyperuseragent-1.1.1.dist-info/RECORD
