Metadata-Version: 2.4
Name: HyperUserAgent
Version: 1.1.1
Summary: Hyper-UA ─ ultra-realistic User-Agent & fingerprint generator.
Home-page: https://github.com/TheHritu/HyperUserAgent
Author: Hritu
Author-email: hrituraj5717@gmail.com
License: MIT
Classifier: Programming Language :: Python :: 3
Classifier: Operating System :: OS Independent
Classifier: License :: OSI Approved :: MIT License
Classifier: Development Status :: 3 - Alpha
Classifier: Intended Audience :: Developers
Classifier: Topic :: Software Development :: Libraries
Requires-Python: >=3.8
License-File: LICENSE
Requires-Dist: httpx==0.28.1
Requires-Dist: Pillow==11.3.0
Requires-Dist: PyYAML==6.0.2
Dynamic: author
Dynamic: author-email
Dynamic: classifier
Dynamic: description
Dynamic: description-content-type
Dynamic: home-page
Dynamic: license
Dynamic: license-file
Dynamic: requires-dist
Dynamic: requires-python
Dynamic: summary
